py3dcore/__init__.py
py3dcore/_extcuda.py
py3dcore/_extmath.py
py3dcore/_extnumba.py
py3dcore/model.py
py3dcore/params.py
py3dcore/rotqs.py
py3dcore/util.py
py3dcore/fitting/__init__.py
py3dcore/fitting/fitter.py
py3dcore/fitting/util.py
py3dcore/fitting/methods/__init__.py
py3dcore/fitting/methods/abcsmc.py
py3dcore/fitting/methods/abcsmc_psd.py
py3dcore/fitting/methods/abcsmc_v1.py
py3dcore/fitting/methods/smc.py
py3dcore/fitting/methods/summary.py
py3dcore/models/__init__.py
py3dcore/models/ttghv0/__init__.py
py3dcore/models/ttghv0/coordinates.py
py3dcore/models/ttghv0/magfield.py
py3dcore/models/ttghv0/parameters.json
py3dcore/models/ttghv0/propagation.py
py3dcore/models/ttghv1/__init__.py
py3dcore/models/ttghv1/coordinates.py
py3dcore/models/ttghv1/magfield.py
py3dcore/models/ttghv1/parameters.json
py3dcore/models/ttghv1/propagation.py
py3dcore/models/ttghv2/__init__.py
py3dcore/models/ttghv2/coordinates.py
py3dcore/models/ttghv2/magfield.py
py3dcore/models/ttghv2/parameters.json
py3dcore/models/ttghv2/propagation.py
py3dcore/models/ttghv2t/__init__.py
py3dcore/models/ttghv2t/magfield.py
py3dcore/models/ttghv2t/parameters.json
py3dcore/models/ttghv3/__init__.py
py3dcore/models/ttghv3/coordinates.py
py3dcore/models/ttghv3/magfield.py
py3dcore/models/ttghv3/parameters.json
py3dcore/models/ttghv3/propagation.py
py3dcore/models/ttncv2/__init__.py
py3dcore/models/ttncv2/coordinates.py
py3dcore/models/ttncv2/magfield.py
py3dcore/models/ttncv2/parameters.json
py3dcore/models/ttncv2/propagation.py
py3dcore/raytracing/__init__.py
py3dcore/raytracing/raytracing.py
3DCORE-1.1.4.dist-info/LICENSE
3DCORE-1.1.4.dist-info/METADATA
3DCORE-1.1.4.dist-info/WHEEL
3DCORE-1.1.4.dist-info/top_level.txt
3DCORE-1.1.4.dist-info/RECORD
